{
  "READ_THIS_FIRST": {
    "instruction_for_ai": "DO NOT calculate totals from individual activities. Use the pre-calculated values in 'summary', 'weekly_summary', and 'derived_metrics' sections below. These are already computed accurately from the API data.",
    "data_period": "Last 7 days (including today)",
    "extended_data_note": "ACWR and baselines calculated from 28 days of data",
    "capability_metrics_note": "The 'capability' block in derived_metrics contains durability trend (aggregate decoupling 7d/28d) and TID comparison (7d vs 28d distribution drift). These measure HOW the athlete expresses fitness, not just load. Use these for coaching context alongside traditional load metrics. Durability trend direction matters more than absolute values.",
    "quick_stats": {
      "total_training_hours": 2.07,
      "total_activities": 4,
      "total_tss": 83
    }
  },
  "metadata": {
    "athlete_id": "REDACTED",
    "last_updated": "2026-03-17T18:07:50.250579",
    "data_range_days": 7,
    "extended_range_days": 28,
    "version": "3.5.1"
  },
  "alerts": [
    {
      "metric": "acwr",
      "value": 0.42,
      "severity": "alarm",
      "threshold": "0.75 / 1.35",
      "context": "ACWR 0.42 outside safe range. Injury/overreach risk elevated.",
      "persistence_days": null,
      "tier": 2
    },
    {
      "metric": "tid_distribution",
      "value": "Base",
      "severity": "warning",
      "threshold": "7d/28d classification mismatch",
      "context": "TID shift: 7d Base vs 28d Pyramidal. Training distribution changing.",
      "persistence_days": null,
      "tier": 3
    }
  ],
  "history": {
    "available": true,
    "last_generated": "2026-02-26",
    "age_days": 19,
    "total_months": 35,
    "history_confidence": "high"
  },
  "summary": {
    "period_description": "Last 7 days of training (including today)",
    "note": "Duration calculated from API moving_time field.",
    "total_duration_decimal_hours": 2.07,
    "total_activities": 4,
    "by_activity_type": {
      "Ride": {
        "duration_decimal_hours": 0.58,
        "count": 1,
        "tss": 17,
        "distance_km": 14.2
      },
      "Run": {
        "duration_decimal_hours": 0.93,
        "count": 2,
        "tss": 39,
        "distance_km": 8.2
      },
      "TrailRun": {
        "duration_decimal_hours": 0.56,
        "count": 1,
        "tss": 27,
        "distance_km": 4.3
      }
    }
  },
  "current_status": {
    "fitness": {
      "ctl": 26.71,
      "atl": 19.63,
      "tsb": 7.08,
      "ramp_rate": -2.56,
      "fitness_source": "From Intervals.icu API (reflects completed workouts)"
    },
    "thresholds": {
      "ftp_outdoor": 200,
      "ftp_indoor": null,
      "eftp": 173.1,
      "lthr": 154,
      "max_hr": 177,
      "w_prime": 13642,
      "w_prime_kj": 13.6,
      "p_max": 398,
      "vo2max": 50.0
    },
    "current_metrics": {
      "weight_kg": 73.8,
      "resting_hr": 55,
      "hrv": 23.0,
      "sleep_quality": 3,
      "sleep_hours": 7.42
    }
  },
  "derived_metrics": {
    "recovery_index": 0.86,
    "hrv_baseline_7d": 27.0,
    "rhr_baseline_7d": 55.7,
    "hrv_baseline_28d": 25.4,
    "rhr_baseline_28d": 55.5,
    "latest_hrv": 23.0,
    "latest_rhr": 55,
    "acwr": 0.42,
    "acwr_interpretation": "undertraining",
    "monotony": 0.58,
    "monotony_interpretation": "normal",
    "primary_sport": "run",
    "primary_sport_monotony": null,
    "primary_sport_tss_7d": 66.0,
    "effective_monotony": 0.58,
    "multi_sport_detected": true,
    "strain": 48.0,
    "stress_tolerance": 0.8,
    "load_recovery_ratio": 1.0,
    "tss_7d_total": 83.0,
    "tss_28d_total": 788.0,
    "zone_distribution_7d": {
      "z1_hours": 1.72,
      "z2_hours": 0.34,
      "z3_hours": 0.01,
      "z4_plus_hours": 0.0,
      "total_hours": 2.07
    },
    "grey_zone_percentage": 0.3,
    "grey_zone_note": "Gray Zone % (Z3/tempo) - minimize in polarized training",
    "quality_intensity_percentage": 0.0,
    "quality_intensity_note": "Quality Intensity % (Z4+/threshold+) - target ~20% in polarized training",
    "polarisation_index": 1.0,
    "polarisation_note": "Easy time (Z1+Z2) / Total - target ~80% in polarized training",
    "hard_days_this_week": 0,
    "hard_days_note": "Zone ladder: z3+ >= 30min, z4+ >= 10min, z5+ >= 5min, z6+ >= 2min, z7 >= 1min. Cumulative thresholds per Seiler/Foster \u2014 higher zones need less time to qualify as hard",
    "seiler_tid_7d": {
      "z1_seconds": 7420,
      "z2_seconds": 26,
      "z3_seconds": 0,
      "z1_pct": 99.7,
      "z2_pct": 0.3,
      "z3_pct": 0.0,
      "polarization_index": null,
      "classification": "Base"
    },
    "seiler_tid_7d_primary": {
      "z1_seconds": 5348,
      "z2_seconds": 0,
      "z3_seconds": 0,
      "z1_pct": 100.0,
      "z2_pct": 0.0,
      "z3_pct": 0.0,
      "polarization_index": null,
      "classification": "Base",
      "sport": "run"
    },
    "seiler_tid_28d": {
      "z1_seconds": 52158,
      "z2_seconds": 6996,
      "z3_seconds": 3753,
      "z1_pct": 82.9,
      "z2_pct": 11.1,
      "z3_pct": 6.0,
      "polarization_index": null,
      "classification": "Pyramidal"
    },
    "seiler_tid_28d_primary": {
      "z1_seconds": 32829,
      "z2_seconds": 1662,
      "z3_seconds": 3753,
      "z1_pct": 85.8,
      "z2_pct": 4.3,
      "z3_pct": 9.8,
      "polarization_index": 2.29,
      "classification": "Polarized",
      "sport": "run"
    },
    "capability": {
      "durability": {
        "mean_decoupling_7d": null,
        "mean_decoupling_28d": null,
        "high_drift_count_7d": 0,
        "high_drift_count_28d": 0,
        "qualifying_sessions_7d": 0,
        "qualifying_sessions_28d": 0,
        "trend": null,
        "note": "Steady-state power sessions only (VI <= 1.05, VI > 0, >= 90min, power data). Negative decoupling = strong durability. Trend compares 7d vs 28d mean (+/-1% = stable)."
      },
      "tid_comparison": {
        "classification_7d": "Base",
        "classification_28d": "Pyramidal",
        "pi_7d": null,
        "pi_28d": null,
        "pi_delta": null,
        "drift": "shifting",
        "note": "Compares 7d vs 28d Seiler TID to detect distribution shifts. pi_delta positive = more polarized acutely."
      }
    },
    "consistency_index": null,
    "consistency_details": {
      "planned_days": 0,
      "completed_days": 1,
      "matched_days": 0,
      "note": "No planned workouts in period"
    },
    "phase_detected": "Taper",
    "phase_triggers": [
      "TSB 7.08 positive",
      "CTL stable/declining"
    ],
    "seasonal_context": "Late Base / Build",
    "benchmark_indoor": {
      "current_ftp": null,
      "ftp_8_weeks_ago": null,
      "benchmark_index": null,
      "benchmark_percentage": null,
      "seasonal_expected": null
    },
    "benchmark_outdoor": {
      "current_ftp": 200,
      "ftp_8_weeks_ago": null,
      "benchmark_index": null,
      "benchmark_percentage": null,
      "seasonal_expected": null
    },
    "eftp": 173.1,
    "w_prime": 13642,
    "w_prime_kj": 13.6,
    "p_max": 398,
    "power_model_source": "wellness.sportInfo",
    "vo2max": 50.0,
    "calculation_timestamp": "2026-03-17T18:07:50.249752",
    "data_quality": {
      "hrv_data_points": 7,
      "rhr_data_points": 7,
      "activities_7d": 4,
      "activities_28d": 28,
      "planned_workouts_7d": 0,
      "ftp_history_days": {
        "indoor": 0,
        "outdoor": 0
      }
    }
  },
  "recent_activities": [
    {
      "id": "activity_1",
      "date": "2026-03-17T18:10:40",
      "type": "TrailRun",
      "name": "Training Session",
      "duration_hours": 0.56,
      "distance_km": 4.26,
      "tss": 27,
      "intensity_factor": 69.43651,
      "avg_power": null,
      "normalized_power": null,
      "avg_hr": 132,
      "max_hr": 143,
      "avg_cadence": 78.42972,
      "avg_speed": 7.6,
      "max_speed": 11.5,
      "avg_pace": null,
      "avg_temp": 4.8574667,
      "weather": null,
      "humidity": null,
      "wind_speed": 2.4469821,
      "work_kj": null,
      "calories": 358,
      "carbs_used": null,
      "carbs_ingested": null,
      "variability_index": null,
      "decoupling": null,
      "elevation_m": 184.0,
      "feel": null,
      "rpe": null,
      "zone_distribution": {
        "hr_zones": {
          "z1_time": 1394,
          "z2_time": 616,
          "z3_time": 0,
          "z4_time": 0,
          "z5_time": 0
        }
      }
    },
    {
      "id": "activity_2",
      "date": "2026-03-17T08:32:14",
      "type": "Ride",
      "name": "Training Session",
      "duration_hours": 0.58,
      "distance_km": 14.2,
      "tss": 17,
      "intensity_factor": 53.91997,
      "avg_power": null,
      "normalized_power": null,
      "avg_hr": 110,
      "max_hr": 142,
      "avg_cadence": 79.2225,
      "avg_speed": 24.4,
      "max_speed": 37.6,
      "avg_pace": null,
      "avg_temp": 6.9150734,
      "weather": null,
      "humidity": null,
      "wind_speed": 2.6209857,
      "work_kj": null,
      "calories": 245,
      "carbs_used": null,
      "carbs_ingested": null,
      "variability_index": null,
      "decoupling": null,
      "elevation_m": 132.0,
      "feel": null,
      "rpe": null,
      "zone_distribution": {
        "hr_zones": {
          "z1_time": 2023,
          "z2_time": 49,
          "z3_time": 26,
          "z4_time": 0,
          "z5_time": 0
        }
      }
    },
    {
      "id": "activity_3",
      "date": "2026-03-16T14:55:09",
      "type": "Run",
      "name": "Training Session",
      "duration_hours": 0.43,
      "distance_km": 3.73,
      "tss": 19,
      "intensity_factor": 59.470257,
      "avg_power": null,
      "normalized_power": null,
      "avg_hr": 124,
      "max_hr": 140,
      "avg_cadence": 80.498604,
      "avg_speed": 6.9,
      "max_speed": 14.2,
      "avg_pace": null,
      "avg_temp": 8.499761,
      "weather": null,
      "humidity": null,
      "wind_speed": 1.323073,
      "work_kj": null,
      "calories": 316,
      "carbs_used": null,
      "carbs_ingested": null,
      "variability_index": null,
      "decoupling": null,
      "elevation_m": 64.0,
      "feel": null,
      "rpe": null,
      "zone_distribution": {
        "hr_zones": {
          "z1_time": 1287,
          "z2_time": 267,
          "z3_time": 0,
          "z4_time": 0,
          "z5_time": 0
        }
      }
    },
    {
      "id": "activity_4",
      "date": "2026-03-16T13:52:51",
      "type": "Run",
      "name": "Training Session",
      "duration_hours": 0.5,
      "distance_km": 4.44,
      "tss": 20,
      "intensity_factor": 55.41085,
      "avg_power": null,
      "normalized_power": null,
      "avg_hr": 123,
      "max_hr": 147,
      "avg_cadence": 81.144516,
      "avg_speed": 6.8,
      "max_speed": 13.9,
      "avg_pace": null,
      "avg_temp": 8.300493,
      "weather": null,
      "humidity": null,
      "wind_speed": 3.003661,
      "work_kj": null,
      "calories": 398,
      "carbs_used": null,
      "carbs_ingested": null,
      "variability_index": null,
      "decoupling": null,
      "elevation_m": 72.0,
      "feel": null,
      "rpe": null,
      "zone_distribution": {
        "hr_zones": {
          "z1_time": 1485,
          "z2_time": 299,
          "z3_time": 0,
          "z4_time": 0,
          "z5_time": 0
        }
      }
    }
  ],
  "wellness_data": [
    {
      "date": "2026-03-11",
      "weight_kg": null,
      "resting_hr": 56,
      "hrv_rmssd": 31.0,
      "hrv_sdnn": null,
      "sleep_hours": 10.0,
      "sleep_quality": 3,
      "sleep_score": 73.0,
      "mental_energy": null,
      "fatigue": null,
      "soreness": null,
      "avg_sleeping_hr": null,
      "vo2max": null
    },
    {
      "date": "2026-03-12",
      "weight_kg": null,
      "resting_hr": 60,
      "hrv_rmssd": 28.0,
      "hrv_sdnn": null,
      "sleep_hours": 6.68,
      "sleep_quality": 3,
      "sleep_score": 65.0,
      "mental_energy": null,
      "fatigue": null,
      "soreness": null,
      "avg_sleeping_hr": null,
      "vo2max": null
    },
    {
      "date": "2026-03-13",
      "weight_kg": 72.7,
      "resting_hr": 55,
      "hrv_rmssd": 32.0,
      "hrv_sdnn": null,
      "sleep_hours": 8.61,
      "sleep_quality": 3,
      "sleep_score": 78.0,
      "mental_energy": null,
      "fatigue": null,
      "soreness": null,
      "avg_sleeping_hr": null,
      "vo2max": null
    },
    {
      "date": "2026-03-14",
      "weight_kg": 73.0,
      "resting_hr": 53,
      "hrv_rmssd": 24.0,
      "hrv_sdnn": null,
      "sleep_hours": 7.36,
      "sleep_quality": 2,
      "sleep_score": 82.0,
      "mental_energy": null,
      "fatigue": null,
      "soreness": null,
      "avg_sleeping_hr": null,
      "vo2max": null
    },
    {
      "date": "2026-03-15",
      "weight_kg": 73.3,
      "resting_hr": 56,
      "hrv_rmssd": 25.0,
      "hrv_sdnn": null,
      "sleep_hours": 7.3,
      "sleep_quality": 3,
      "sleep_score": 70.0,
      "mental_energy": null,
      "fatigue": null,
      "soreness": null,
      "avg_sleeping_hr": null,
      "vo2max": null
    },
    {
      "date": "2026-03-16",
      "weight_kg": null,
      "resting_hr": 55,
      "hrv_rmssd": 26.0,
      "hrv_sdnn": null,
      "sleep_hours": 6.43,
      "sleep_quality": 3,
      "sleep_score": 75.0,
      "mental_energy": null,
      "fatigue": null,
      "soreness": null,
      "avg_sleeping_hr": null,
      "vo2max": 51.0
    },
    {
      "date": "2026-03-17",
      "weight_kg": 73.8,
      "resting_hr": 55,
      "hrv_rmssd": 23.0,
      "hrv_sdnn": null,
      "sleep_hours": 7.42,
      "sleep_quality": 3,
      "sleep_score": 77.0,
      "mental_energy": null,
      "fatigue": null,
      "soreness": null,
      "avg_sleeping_hr": null,
      "vo2max": 50.0
    }
  ],
  "planned_workouts": [],
  "weekly_summary": {
    "total_training_hours": 2.07,
    "total_tss": 83,
    "activities_count": 4,
    "avg_hrv": 27.0,
    "avg_resting_hr": 55.7
  },
  "race_calendar": {
    "next_race": null,
    "all_races": [],
    "taper_alert": {
      "active": false
    },
    "race_week": {
      "active": false
    }
  }
}